Team_14_pipe/codes/DataMem.v
module DataMem(
    input clk, reset, MemRead, MemWrite,
    input [9:0] address,
    input [63:0] write_data,
    output reg [63:0] read_data
);

reg [7:0] Memory[1023:0];

initial begin
    for(integer i = 0;i<1024;i=i+1) begin
        Memory[i] = 8'h00;
    end
end

always@(posedge clk) begin
    if(reset) begin
        read_data <= 64'h0000000000000000;
    end
    else if(MemWrite) begin // writing:
        Memory[address] <= write_data[63:56];
        Memory[address+1] <= write_data[55:48];
        Memory[address+2] <= write_data[47:40];
        Memory[address+3] <= write_data[39:32];
        Memory[address+4] <= write_data[31:24];
        Memory[address+5] <= write_data[23:16];
        Memory[address+6] <= write_data[15:8];
        Memory[address+7] <= write_data[7:0];
    end
end
always@(*) begin
    if(MemRead) begin // reading:
        read_data = {Memory[address], Memory[address+1], 
                    Memory[address+2], Memory[address+3], 
                    Memory[address+4], Memory[address+5], 
                    Memory[address+6], Memory[address+7]};
    end
end
// following not allowed since in one line of assign, we cannot access
// more than one address of an unpacked array
// assign read_data = {Memory[address], Memory[address+5'd1], Memory[address+5'd2], Memory[address+5'd3], Memory[address+5'd4], Memory[address+5'd5], Memory[address+5'd6], Memory[address+5'd7]};

endmodule

Team_14_pipe/codes/DataMem_tb.v
`timescale 1ns/1ps
`include "DataMem.v"

module DataMem_tb;
    reg clk, reset, MemRead, MemWrite;
    reg [9:0] address;
    reg [63:0] write_data;
    wire [63:0] read_data;
    integer pass_count = 0, total_tests = 4;
    integer file_handle;

    DataMem uut(.clk(clk), .reset(reset), .MemRead(MemRead), .MemWrite(MemWrite),
                .address(address), .write_data(write_data), .read_data(read_data));

    initial begin
        clk = 0;
        forever #5 clk = ~clk;
    end

    task run_test;
        input [4:0] test_number;
        input [9:0] addr;
        input [63:0] wdata, exp_read_data;
        begin
            // Write
            MemWrite = 1; MemRead = 0;
            address = addr; write_data = wdata;
            // following line of code tells simulation to
            // stop till the next clock positive edge is seen,
            // so that the inputs asserted to the data memory can
            // be first written in the writing cycle
            // and then the read logic is started after waiting 
            // for #1 delay after the clk posedge.. so that after 
            // writing we can let the data be written in memory
            // in stable manner....
            @(posedge clk); #1;
            // Read
            // if we exclude #1 after @(posedge clk),
            // we can still get same functionality by writing:
            // @(posedge clk);
            // MemWrite <= 0; MemRead <= 1;
            // address <= addr;
            // This non blocking assignment happens only
            // after the delay element has waited and
            // safely stabilized.
            MemWrite = 0; MemRead = 1;
            address = addr; #1;
            $display("Test %0d: wrote %016h to addr=%0d, read back=%016h",
                     test_number, wdata, addr, read_data);
            if (read_data === exp_read_data) begin
                pass_count = pass_count + 1;
                $fdisplay(file_handle, "Test %0d, Status: PASS", test_number);
            end else begin
                $fdisplay(file_handle, "Test %0d, Status: FAIL (exp_read_data %016h got %016h)",
                          test_number, exp_read_data, read_data);
                $display("Expected: read_data=%016h", exp_read_data);
                $display("Got:      read_data=%016h\n", read_data);
            end
        end
    endtask

    initial begin
        file_handle = $fopen("DataMem_results.txt", "w");
        if (file_handle == 0) begin
            $display("Error: Could not open file.");
            $finish;
        end
        $dumpfile("DataMem_tb.vcd");
        $dumpvars(0, DataMem_tb);
        pass_count=0;

        reset = 1; MemRead = 0; MemWrite = 0;
        @(posedge clk); #1; reset = 0;

        run_test(1, 10'd10, 64'h000000000000000F, 64'h000000000000000F); // store/load 15
        run_test(2, 10'd20, 64'hA5A5A5A55A5A5A5A, 64'hA5A5A5A55A5A5A5A); // Alternating bit pattern
        run_test(3, 10'd100, 64'hFFFFFFFFFFFFFFFF, 64'hFFFFFFFFFFFFFFFF); // all ones
        run_test(4, 10'd0, 64'd0, 64'd0); // zero value

        $display("Passed %0d/%0d tests", pass_count, total_tests);
        $fdisplay(file_handle, "Passed %0d/%0d tests", pass_count, total_tests);
        $fclose(file_handle);
        #10; $finish;
    end
endmodule

Team_14_pipe/codes/DataMem_tb.vcd
$date
	Sun Feb 22 20:52:13 2026
$end
$version
	Icarus Verilog
$end
$timescale
	1ps
$end
$scope module DataMem_tb $end
$var wire 64 ! read_data [63:0] $end
$var reg 1 " MemRead $end
$var reg 1 # MemWrite $end
$var reg 10 $ address [9:0] $end
$var reg 1 % clk $end
$var reg 1 & reset $end
$var reg 64 ' write_data [63:0] $end
$var integer 32 ( file_handle [31:0] $end
$var integer 32 ) pass_count [31:0] $end
$var integer 32 * total_tests [31:0] $end
$scope module uut $end
$var wire 1 " MemRead $end
$var wire 1 # MemWrite $end
$var wire 10 + address [9:0] $end
$var wire 1 % clk $end
$var wire 1 & reset $end
$var wire 64 , write_data [63:0] $end
$var reg 64 - read_data [63:0] $end
$scope begin $ivl_for_loop0 $end
$var integer 32 . i [31:0] $end
$upscope $end
$upscope $end
$scope task run_test $end
$var reg 10 / addr [9:0] $end
$var reg 64 0 exp_read_data [63:0] $end
$var reg 5 1 test_number [4:0] $end
$var reg 64 2 wdata [63:0] $end
$upscope $end
$upscope $end
$enddefinitions $end
$comment Show the parameter values. $end
$dumpall
$end
#0
$dumpvars
bx 2
bx 1
bx 0
bx /
b10000000000 .
bx -
bx ,
bx +
b100 *
b0 )
b10000000000000000000000000000011 (
bx '
1&
0%
bx $
0#
0"
bx !
$end
#5000
b0 !
b0 -
1%
#6000
b1111 '
b1111 ,
b1010 $
b1010 +
1#
b1111 0
b1111 2
b1010 /
b1 1
0&
#10000
0%
#15000
1%
#16000
b1111 !
b1111 -
1"
0#
#17000
b1010010110100101101001011010010101011010010110100101101001011010 '
b1010010110100101101001011010010101011010010110100101101001011010 ,
b10100 $
b10100 +
0"
1#
b1010010110100101101001011010010101011010010110100101101001011010 0
b1010010110100101101001011010010101011010010110100101101001011010 2
b10100 /
b10 1
b1 )
#20000
0%
#25000
1%
#26000
b1010010110100101101001011010010101011010010110100101101001011010 !
b1010010110100101101001011010010101011010010110100101101001011010 -
1"
0#
#27000
b1111111111111111111111111111111111111111111111111111111111111111 '
b1111111111111111111111111111111111111111111111111111111111111111 ,
b1100100 $
b1100100 +
0"
1#
b1111111111111111111111111111111111111111111111111111111111111111 0
b1111111111111111111111111111111111111111111111111111111111111111 2
b1100100 /
b11 1
b10 )
#30000
0%
#35000
1%
#36000
b1111111111111111111111111111111111111111111111111111111111111111 !
b1111111111111111111111111111111111111111111111111111111111111111 -
1"
0#
#37000
b0 '
b0 ,
b0 $
b0 +
0"
1#
b0 0
b0 2
b0 /
b100 1
b11 )
#40000
0%
#45000
1%
#46000
b0 !
b0 -
1"
0#
#47000
b100 )
