Team_14_pipe/PC.v
module PC(
    input clk, reset,
    input [63:0] pc_in,
    output reg [63:0] pc_out
);
    always@(posedge clk) begin
        if(reset)
            pc_out <= 64'h0000;
        else
            pc_out <= pc_in;
    end
endmodule

Team_14_pipe/PC_tb.v
`timescale 1ns/1ps
`include "PC.v"

module PC_tb;
    reg clk, reset;
    reg [63:0] pc_in;
    wire [63:0] pc_out;
    integer pass_count = 0, total_tests = 4;
    integer file_handle;

    PC uut(.clk(clk), .reset(reset), .pc_in(pc_in), .pc_out(pc_out));

    initial begin
        clk = 0;
        forever #5 clk = ~clk;
    end

    task run_test;
        input [4:0] test_number;
        input [63:0] test_pc_in, exp_pc_out;
        input test_reset;
        begin
            reset = test_reset; pc_in = test_pc_in;
            // we assert the values of inputs to this PC register
            // and wait till the net posedge of clk aand after a small delay
            // #1, we observe the outputs of the uut, if they match the
            // expected values, then TC->pass else fail
            @(posedge clk); #1;
            $display("Test %0d: reset=%b pc_in=%016h -> pc_out=%016h",
                     test_number, test_reset, test_pc_in, pc_out);
            if (pc_out === exp_pc_out) begin
                pass_count = pass_count + 1;
                $fdisplay(file_handle, "Test %0d, Status: PASS", test_number);
            end else begin
                $fdisplay(file_handle, "Test %0d, Status: FAIL (expected %016h got %016h)",
                          test_number, exp_pc_out, pc_out);
                $display("Expected: pc_out=%016h", exp_pc_out);
                $display("Got:      pc_out=%016h\n", pc_out);
            end
        end
    endtask

    initial begin
        file_handle = $fopen("PC_results.txt", "w");
        if (file_handle == 0) begin
            $display("Error: Could not open file.");
            $finish;
        end
        
        $dumpfile("PC_tb.vcd");
        $dumpvars(0, PC_tb);
        pass_count = 0;

        run_test(1, 64'd0, 64'd0, 1); // reset asserted and then other tc's run
        run_test(2, 64'd4, 64'd4, 0); // normal advance
        run_test(3, 64'd8, 64'd8, 0); // normal advance
        run_test(4, 64'd100, 64'd0, 1); // reset overrides pc_in

        $display("Passed %0d/%0d tests", pass_count, total_tests);
        $fdisplay(file_handle, "Passed %0d/%0d tests", pass_count, total_tests);
        $fclose(file_handle);
        #10; $finish;
    end
endmodule

Team_14_pipe/PC_tb.vcd
$date
	Sun Feb 22 19:40:15 2026
$end
$version
	Icarus Verilog
$end
$timescale
	1ps
$end
$scope module PC_tb $end
$var wire 64 ! pc_out [63:0] $end
$var reg 1 " clk $end
$var reg 64 # pc_in [63:0] $end
$var reg 1 $ reset $end
$var integer 32 % file_handle [31:0] $end
$var integer 32 & pass_count [31:0] $end
$var integer 32 ' total_tests [31:0] $end
$scope module uut $end
$var wire 1 " clk $end
$var wire 64 ( pc_in [63:0] $end
$var wire 1 $ reset $end
$var reg 64 ) pc_out [63:0] $end
$upscope $end
$scope task run_test $end
$var reg 64 * exp_pc_out [63:0] $end
$var reg 5 + test_number [4:0] $end
$var reg 64 , test_pc_in [63:0] $end
$var reg 1 - test_reset $end
$upscope $end
$upscope $end
$enddefinitions $end
$comment Show the parameter values. $end
$dumpall
$end
#0
$dumpvars
1-
b0 ,
b1 +
b0 *
bx )
b0 (
b100 '
b0 &
b10000000000000000000000000000011 %
1$
b0 #
0"
bx !
$end
#5000
b0 !
b0 )
1"
#6000
b100 #
b100 (
0$
0-
b100 *
b100 ,
b10 +
b1 &
#10000
0"
#15000
b100 !
b100 )
1"
#16000
b1000 #
b1000 (
b1000 *
b1000 ,
b11 +
b10 &
#20000
0"
#25000
b1000 !
b1000 )
1"
#26000
b1100100 #
b1100100 (
1$
1-
b0 *
b1100100 ,
b100 +
b11 &
#30000
0"
#35000
b0 !
b0 )
1"
#36000
b100 &
